{
  "version": 1,
  "serviceConfiguration": {
    "serviceName": "AppSync",
    "defaultAuthType": {
      "mode": "API_KEY",
      "keyDescription": "api key description",
      "expirationTime": 30
    },
    "conflictResolution": {
      "defaultResolutionStrategy": {
        "type": "AUTOMERGE"
      }
    },
    "apiName": "fromwear",
    "gqlSchemaPath": "/tmp/amplify-e91e2a99-8788-45c0-9463-cf9f44235300/amplify/backend/api/fromwear/schema.graphql",
    "additionalAuthTypes": [
      {
        "mode": "AWS_IAM"
      },
      {
        "mode": "AMAZON_COGNITO_USER_POOLS",
        "cognitoUserPoolId": "authfromwear7157cfba"
      }
    ]
  }
}